clipx/__init__.py
clipx/cli.py
clipx/core.py
clipx/models/__init__.py
clipx/models/cascadepsp_test.py
clipx/models/cascadepsp/__init__.py
clipx/models/cascadepsp/download.py
clipx/models/cascadepsp/eval_helper.py
clipx/models/cascadepsp/main.py
clipx/models/cascadepsp/models/__init__.py
clipx/models/cascadepsp/models/psp/__init__.py
clipx/models/cascadepsp/models/psp/extractors.py
clipx/models/cascadepsp/models/psp/pspnet.py
clipx/models/u2net/__init__.py
clipx/models/u2net/download.py
clipx/models/u2net/main.py
clipx-0.5.0.dist-info/licenses/LICENSE
clipx-0.5.0.dist-info/METADATA
clipx-0.5.0.dist-info/WHEEL
clipx-0.5.0.dist-info/entry_points.txt
clipx-0.5.0.dist-info/top_level.txt
clipx-0.5.0.dist-info/RECORD
