Metadata-Version: 2.4
Name: clipx
Version: 0.5.0
Summary: Image background removal tool supporting U2Net and CascadePSP models
Author-email: zhangsdong <zhangsdong0402@gmail.com>
License: MIT
Project-URL: Homepage, https://github.com/zhangsdong/clipx
Project-URL: Bug Tracker, https://github.com/zhangsdong/clipx/issues
Project-URL: Source Code, https://github.com/zhangsdong/clipx
Classifier: Development Status :: 4 - Beta
Classifier: Environment :: Console
Classifier: Intended Audience :: Developers
Classifier: License :: OSI Approved :: MIT License
Classifier: Programming Language :: Python :: 3
Classifier: Programming Language :: Python :: 3.8
Classifier: Programming Language :: Python :: 3.9
Classifier: Programming Language :: Python :: 3.10
Classifier: Programming Language :: Python :: 3.11
Classifier: Programming Language :: Python :: 3.12
Classifier: Programming Language :: Python :: 3.13
Classifier: Topic :: Multimedia :: Graphics
Classifier: Topic :: Scientific/Engineering :: Image Processing
Requires-Python: <3.14,>=3.8
License-File: LICENSE
Requires-Dist: torch>=1.7.0
Requires-Dist: torchvision>=0.8.0
Requires-Dist: pillow>=8.0.0
Requires-Dist: numpy>=1.19.0
Requires-Dist: click>=7.1.2
Requires-Dist: requests>=2.25.0
Requires-Dist: tqdm>=4.50.0
Requires-Dist: onnxruntime>=1.8.0
Requires-Dist: pooch>=1.3.0
Requires-Dist: opencv-python>=4.5.0
Dynamic: license-file
